wodby/__init__.py
wodby/api_client.py
wodby/configuration.py
wodby/rest.py
wodby/api/__init__.py
wodby/api/application_api.py
wodby/api/backup_api.py
wodby/api/domain_api.py
wodby/api/git_repository_api.py
wodby/api/instance_api.py
wodby/api/organization_api.py
wodby/api/server_api.py
wodby/api/stack_api.py
wodby/api/task_api.py
wodby/api/user_api.py
wodby/models/__init__.py
wodby/models/app.py
wodby/models/backup.py
wodby/models/backup_file.py
wodby/models/backup_files.py
wodby/models/domain.py
wodby/models/git_repo.py
wodby/models/instance.py
wodby/models/instance_type.py
wodby/models/org.py
wodby/models/request_app_create.py
wodby/models/request_app_create_git.py
wodby/models/request_app_create_services.py
wodby/models/request_instance_create.py
wodby/models/request_instance_create_git.py
wodby/models/request_instance_deploy.py
wodby/models/request_instance_deploy_codebase.py
wodby/models/request_instances_upgrade.py
wodby/models/request_stacks_update.py
wodby/models/response_task.py
wodby/models/response_task_app.py
wodby/models/response_task_instance.py
wodby/models/server.py
wodby/models/stack.py
wodby/models/stack_service.py
wodby/models/stack_service_implementation.py
wodby/models/task.py
wodby/models/user.py
wodby-3.0.13.dist-info/METADATA
wodby-3.0.13.dist-info/WHEEL
wodby-3.0.13.dist-info/top_level.txt
wodby-3.0.13.dist-info/RECORD
