Metadata-Version: 2.1
Name: wodby
Version: 3.0.13
Summary: Wodby API Client
Home-page: https://github.com/wodby/wodby-sdk-python
Author-email: 
Maintainer: Wodby
Maintainer-email: hello@wodby.com
License: UNKNOWN
Keywords: Swagger,Wodby API Client
Platform: UNKNOWN
Requires-Dist: certifi (>=2017.4.17)
Requires-Dist: python-dateutil (>=2.1)
Requires-Dist: six (>=1.10)
Requires-Dist: urllib3 (>=1.23)
